MLPyVersioneer/__init__.py
MLPyVersioneer/__main__.py
MLPyVersioneer/exporter.py
MLPyVersioneer/summary.py
MLPyVersioneer/training_phase_metric.py
MLPyVersioneer/training_phase_metric_storage.py
MLPyVersioneer-1.0.4.dist-info/LICENSE
MLPyVersioneer-1.0.4.dist-info/METADATA
MLPyVersioneer-1.0.4.dist-info/WHEEL
MLPyVersioneer-1.0.4.dist-info/entry_points.txt
MLPyVersioneer-1.0.4.dist-info/top_level.txt
MLPyVersioneer-1.0.4.dist-info/RECORD
