Metadata-Version: 2.1
Name: MLPyVersioneer
Version: 1.0.4
Summary: A Python package for versioning your python machine learning models.
Author-email: Jeppe Berg Axelsen <xfm82gtn@gmail.com>
License: MIT License
Project-URL: Homepage, https://github.com/jaxels20/MLPyVersioneer
Keywords: machine learning,versioning,ml,mlpyversioneer
Classifier: License :: OSI Approved :: MIT License
Classifier: Programming Language :: Python
Classifier: Programming Language :: Python :: 3
Requires-Python: >=3.9
License-File: LICENSE
